Metadata-Version: 2.1
Name: uw-stempals-demos
Version: 0.1.0
Summary: Demo simulations for UW's STEM Pals outreach program.
Home-page: http://github.com/jfcrenshaw/uw_stempals_demos
Author: John Franklin Crenshaw
Author-email: jfc20@uw.edu
License: MIT
Platform: UNKNOWN
Classifier: Programming Language :: Python :: 3
Classifier: License :: OSI Approved :: MIT License
Classifier: Operating System :: OS Independent
Classifier: Intended Audience :: Science/Research
Classifier: Topic :: Scientific/Engineering
Requires-Python: >=3.6.0
Provides-Extra: dev
Provides-Extra: docs
